ifcimglib/__init__.py
ifcimglib/_nbdev.py
ifcimglib/apply.py
ifcimglib/cif2lmdb.py
ifcimglib/cif2tiff.py
ifcimglib/imglmdb.py
ifcimglib/preprocessing.py
ifcimglib/utils.py
ifcimglib-0.1.3.dist-info/LICENSE
ifcimglib-0.1.3.dist-info/METADATA
ifcimglib-0.1.3.dist-info/WHEEL
ifcimglib-0.1.3.dist-info/entry_points.txt
ifcimglib-0.1.3.dist-info/top_level.txt
ifcimglib-0.1.3.dist-info/RECORD
