Metadata-Version: 2.1
Name: ifcimglib
Version: 0.1.3
Summary: Library containing read, and preprocessing functions for imaging flow cytometry images contained in Lightning Memory-mapped Databases (lmdb).
Home-page: https://github.com/mlippeve/ifcimglib/tree/master/
Author: Maxim Lippeveld
Author-email: maxim.lippeveld@ugent.be
License: Apache Software License 2.0
Keywords: lmdb imaging preprocessing
Platform: UNKNOWN
Classifier: Development Status :: 4 - Beta
Classifier: Intended Audience :: Developers
Classifier: License :: OSI Approved :: Apache Software License
Classifier: Natural Language :: English
Classifier: Programming Language :: Python :: 3.6
Classifier: Programming Language :: Python :: 3.7
Classifier: Programming Language :: Python :: 3.8
Requires-Python: >=3.6
Requires-Dist: lmdb
Requires-Dist: python-javabridge
Requires-Dist: numpy
Requires-Dist: pandas
Requires-Dist: matplotlib
Requires-Dist: seaborn
Requires-Dist: jupyterlab
Requires-Dist: nbdev
Requires-Dist: click
Requires-Dist: tqdm
Requires-Dist: python-bioformats
Requires-Dist: opencv-python-headless
Requires-Dist: Pillow
Requires-Dist: flowio
